wbuuidpkg/__init__.py
wbuuidpkg/generator.py
wbuuidpkg/wb_node.js
wbuuidpkg/lib/crypto-js.min.js
wbuuidpkg-0.1.1.dist-info/METADATA
wbuuidpkg-0.1.1.dist-info/WHEEL
wbuuidpkg-0.1.1.dist-info/entry_points.txt
wbuuidpkg-0.1.1.dist-info/top_level.txt
wbuuidpkg-0.1.1.dist-info/RECORD
