Metadata-Version: 2.1
Name: wbuuidpkg
Version: 0.1.1
Summary: Generate encrypted uuid using Node.js script
Home-page: 
Author: yige
Requires-Python: >=3.8
